paddles/__init__.py
paddles/bag.py
paddles/deque.py
paddles/queue.py
paddles/sorting.py
paddles/stack.py
paddles-0.2.0.dist-info/WHEEL
paddles-0.2.0.dist-info/METADATA
paddles-0.2.0.dist-info/RECORD
