Metadata-Version: 2.4
Name: paddles
Version: 0.2.0
Summary: A pedagogical algorithms and data structures library
Keywords: algorithms,data structures,education
Author: Michel Wermelinger
Author-email: Michel Wermelinger <michel.wermelinger@open.ac.uk>
License-Expression: BSD-3-Clause
Classifier: Development Status :: 3 - Alpha
Classifier: Intended Audience :: Education
Classifier: License :: OSI Approved :: BSD License
Classifier: Programming Language :: Python :: 3.10
Classifier: Topic :: Education
Classifier: Topic :: Software Development :: Libraries :: Python Modules
Classifier: Operating System :: OS Independent
Requires-Python: >=3.10
Project-URL: Changelog, https://github.com/dsa-ou/paddles/blob/main/CHANGELOG.md
Project-URL: Homepage, https://dsa-ou.github.io/paddles/
Project-URL: Issues, https://github.com/dsa-ou/paddles/issues
Project-URL: Repository, https://github.com/dsa-ou/paddles
